macos_display/__init__.py
macos_display/display.cpython-38-darwin.so
macos_display-1.1.10.dist-info/LICENSE.rst
macos_display-1.1.10.dist-info/METADATA
macos_display-1.1.10.dist-info/WHEEL
macos_display-1.1.10.dist-info/top_level.txt
macos_display-1.1.10.dist-info/RECORD
