Metadata-Version: 2.1
Name: macos-display
Version: 1.1.10
Summary: Retrieve information about macOS displays
Home-page: https://github.com/sixty-north/macos-display
Author: rob@sixty-north.com
Author-email: rob@sixty-north.com
License: UNKNOWN
Platform: UNKNOWN
Classifier: Development Status :: 3 - Alpha
Classifier: Intended Audience :: Developers
Classifier: License :: OSI Approved :: BSD License
Classifier: Operating System :: MacOS :: MacOS X
Classifier: Programming Language :: Python :: 3
Classifier: License :: OSI Approved :: zlib/libpng License
License-File: LICENSE.rst
Requires-Dist: pybind11
Provides-Extra: dev
Requires-Dist: bump2version ; extra == 'dev'
Requires-Dist: pybind11 ; extra == 'dev'
